{
    "76561197960444220": [
        "rupert",
        "\u039e rupert"
    ],
    "76561197960745148": [
        "6PuckClutch",
        "M/Sgt. 6PuckClutch [",
        "= 6PuckClutch",
        "\u039e 6PuckClutch",
        "ILL Na Na",
        "Im #1",
        "Too Good",
        "The Greatest",
        "Too Damn Good",
        "Truly Epic",
        "\u113f 6PuckClutch",
        "I'm Better Than You",
        "Soo Good",
        "Sh*t Box Commander",
        "\u03a8 6PuckClutch"
    ],
    "76561197962847101": [
        "TakaHara",
        "\u039e TaKaHara",
        "\u2661G\u039eN\u2661 TaKaHara \u30c4"
    ],
    "76561197964656903": [
        "Yifei",
        "CoC.Yifei",
        "p$w | Yifei",
        "\u2302 Yifei",
        "\u2302E Yifei",
        "\u2302 \u98de\u98de",
        "= \u2302 \u98de\u98de",
        "Gensbie \u2615"
    ],
    "76561197964919183": [
        "Killer Tomato",
        "Killertomato",
        "\u039e Killertomato",
        "Tomato"
    ],
    "76561197966086657": [
        "Dash Thirty",
        "\u039e DashThirty"
    ],
    "76561197968217756": [
        "Deco",
        "\u039e Deco",
        "\u2661G\u039eN\u2661 Deco",
        "D\u039eCO"
    ],
    "76561197970620334": [
        "Fault",
        "\u039e Fault"
    ],
    "76561197971103272": [
        "Recyclic",
        "\u039e Recyclic"
    ],
    "76561197972652384": [
        "RonPaul4Prez",
        "\u039e RonPaul4Prez"
    ],
    "76561197978305398": [
        "VonCorndog",
        "= VonCorndog",
        "\u039e VonCorndog"
    ],
    "76561197979969912": [
        "Sikon",
        "\u039e Sikon"
    ],
    "76561197981058624": [
        "Hodge",
        "\u039e Hodge"
    ],
    "76561197982075637": [
        "Spooky",
        "\u039e Spooky"
    ],
    "76561197982325629": [
        "Rando",
        "rando",
        "= rando",
        "\u039e rando",
        "USRangerHater",
        "USRangerFan",
        "His name is US Ranger",
        "\u039e USRager"
    ],
    "76561197982656966": [
        "DriveBy",
        "\u039e DriveBy",
        "Deag Training"
    ],
    "76561197983347294": [
        "Smearin",
        "smearin",
        "\u039e Smearin"
    ],
    "76561197984425850": [
        "GrowlingDuck",
        "\u039e GrowlingDuck"
    ],
    "76561197985365329": [
        "Inchon",
        "\u039e Inchon"
    ],
    "76561197986818505": [
        "shoeless airplane ambasssador",
        "\u2708"
    ],
    "76561197987520744": [
        "Spitfire21",
        "\u039e spitfire21",
        "spitfire21"
    ],
    "76561197988892465": [
        "NothingTooFancy",
        "\u039e NothingTooFancy"
    ],
    "76561197990675137": [
        "Jaeger",
        "\u039e jaeger",
        "cover 6 studio sucks",
        "hunter",
        "hunter_1",
        "Steve1989MREInfo sup",
        "Steve1989MREInfo fan",
        "jaeger",
        "jae"
    ],
    "76561197991251854": [
        "Oreo",
        "O.J.oreo",
        "= Oreo",
        "\u039e Oreo"
    ],
    "76561197991442292": [
        "Klaro",
        "klaro22 [SLO]",
        "klaro22",
        "= Klaro",
        "\u039e Klaro",
        "\u039e Klaro_1"
    ],
    "76561197991665416": [
        "Fortress",
        "\u039e Fortress",
        "\u039e FORTR\u039eSS",
        "\u039e \u2022 Fortress \u2022",
        "\u039e Fortress O--(-.-Q)",
        "\u039e | Fortress\u2122",
        "\u039e Worst MG NA",
        "\u039e Fortress \u2720",
        "\u039e F\u1d0frtress",
        "\u039e F\u2665RTRESS",
        "\u039e F\u2665RTRESS\u2122"
    ],
    "76561197993278593": [
        "1200",
        "\u300b1200",
        "\u039e 1200"
    ],
    "76561197999303768": [
        "Top",
        "\u039e Top"
    ],
    "76561198000235734": [
        "Allfather",
        "ICNN",
        "\u039e Allfather"
    ],
    "76561198004627760": [
        "EvoPlatypus",
        "\u039e EVOplatypus",
        "\u039eVOplatypus",
        "\u2661G\u039eN\u2661 Evo",
        "\u039evo"
    ],
    "76561198004656906": [
        "Burgundy",
        "[BHB] Burgundy"
    ],
    "76561198006728045": [
        "TamaT",
        "TaMaT",
        "=TaMaT",
        "\u039e TaMaT \u039e",
        "\u039e No 1 Rando's Fan \u039e",
        "\u039e BlindTaMaT \u039e"
    ],
    "76561198007104654": [
        "Da_xManimal",
        "\u039e Da_xManimal"
    ],
    "76561198007453893": [
        "ItsAlwaysNow",
        "\u039eItsAlwaysNow",
        "\u039e ItsAlwaysNow"
    ],
    "76561198007483044": [
        "Father Pig",
        "\u039e FatherPig"
    ],
    "76561198007940875": [
        "Digishadow",
        "\u039e Digishadow"
    ],
    "76561198011058801": [
        "Von Mack",
        "[VNGD] VonMack",
        "[VNGD] Murf -fm-",
        "\u300eV\u300fVonMack",
        "\u300eV\u300fVonmack",
        "\u300eV\u300fVonMack\u039ensen"
    ],
    "76561198011609151": [
        "SeaUnicorn",
        "Cpt. SeaUnicorn [10t",
        "= SeaUnicorn",
        "\u039e SeaUnicorn",
        "S\u039eaUnicorn",
        "CWO. SeaUnicorn [10t",
        "\u03a8 S\u039eaUnicorn"
    ],
    "76561198011974730": [
        "ThatOneZombie",
        "That0neZombie",
        "= That0neZombie",
        "\u039e That0neZombie"
    ],
    "76561198015625181": [
        "VRAG",
        "\u039e VRAG"
    ],
    "76561198018261866": [
        "PolloLoco",
        "\u039e PolloLoco",
        "\u2661G\u039eN\u2661 PolloLoco"
    ],
    "76561198018670606": [
        "Joh (Joe)",
        "\u039e Joh",
        "Joh",
        "Solo Player",
        "Solo - No Join Pls",
        "\ud83c\udf83Halloween Joh\ud83c\udf83",
        "\u039e \ud83c\udf83Halloween Joh\ud83c\udf83",
        "SOLO PLS GOD",
        "ESPT Joh",
        "Verflucht \u2020LEGGENDAR",
        "Verflucht"
    ],
    "76561198018717847": [
        "-UsRanger-",
        "\u039e UsRanger",
        "Ranger raccoon",
        "Ranger Raccoon",
        "\u2661G\u039eN\u2661 UsRanger",
        "\u039e Wambamshabamo",
        "\u039e UsRanger_1"
    ],
    "76561198023246950": [
        "Ice",
        "\u2111\ud835\udd20\ud835\udd22"
    ],
    "76561198023632395": [
        "Convenant",
        "Vex",
        "= Vex",
        "\u039e Vex"
    ],
    "76561198023676623": [
        "Clownface",
        "\u039e Clownface"
    ],
    "76561198033197174": [
        "Zoom",
        "\u039e Zoom"
    ],
    "76561198033514164": [
        "Invader",
        "\u039e Invader",
        "twitch.tv/invadoz"
    ],
    "76561198033766299": [
        "TexasToast",
        "[EASY] TexasToast",
        "=TexasToast",
        "T\u039exasToast"
    ],
    "76561198034641426": [
        "Julius",
        "= Julius",
        "\u039e Julius"
    ],
    "76561198035678348": [
        "Texas Red",
        "\u039e Texas Red"
    ],
    "76561198036321836": [
        "DC_Fireman",
        "DC_Fire_Man",
        "DC_FIR\u039eMan"
    ],
    "76561198037392984": [
        "Glenar",
        "\u039e Glenar"
    ],
    "76561198038980722": [
        "HitmanAlex",
        "\u039e HITMANAlex"
    ],
    "76561198040448722": [
        "I3ammin",
        "|3ammin",
        "\u039e |3AMMIN \u039e",
        "The Grinch"
    ],
    "76561198041267218": [
        "Ozzinator",
        "\u039e Ozzinator"
    ],
    "76561198041743313": [
        "PaaaRadox",
        "//PaaaRADOX",
        "PaaaRADOX",
        "syn | PaaaRADOX",
        "\uff92PaaaRADOX",
        "\uff92 PaaaRADOX",
        "\u039e PaaaRADOX"
    ],
    "76561198042428742": [
        "Burger",
        "\u039e Burger"
    ],
    "76561198042604429": [
        "Lt. Bubbles",
        "\u039e Lt. Bubbles"
    ],
    "76561198044483471": [
        "Pistol27Pete",
        "\u039e pistol27pete"
    ],
    "76561198046843591": [
        "Sneaky"
    ],
    "76561198052119452": [
        "Tsuraisang",
        "[Merc] Tsuraisang",
        "\u039e tsuraisang"
    ],
    "76561198052130515": [
        "SaintPepsi",
        "\u039e SaintPepsi94"
    ],
    "76561198054273218": [
        "MarsRover",
        "\u039e MarsRover",
        "\u039e NipTape",
        "\u039e Marsrover"
    ],
    "76561198055791490": [
        "T_Rah",
        "\u039e T_RAH"
    ],
    "76561198057065558": [
        "Gamalixious",
        "\u039e Gamalixious"
    ],
    "76561198062837577": [
        "Tacsquatch",
        "\u2261Tacsquatch\u2261",
        "Tacsquatch-\u6d6a",
        "= Tacsquatch",
        "\u039e Tacsquatch"
    ],
    "76561198065264060": [
        "Habanero",
        "Habenaro",
        "\u039e Habanero",
        "\u039e The UsRanger"
    ],
    "76561198069015452": [
        "Drone",
        "\u039e Drone"
    ],
    "76561198069985731": [
        "Crimz",
        "\u043d\u0455 | Crimz",
        "-TL- Crimz",
        "\u039e Crimz"
    ],
    "76561198071842760": [
        "Veni Vici",
        "\u039e Veni Vici",
        "PV || Veni Vici"
    ],
    "76561198074575454": [
        "Jose ARCtico",
        "\u039e Jose ARCtico"
    ],
    "76561198076402505": [
        "JJJ (Cru)",
        "\u039e jjjj",
        "jjjj",
        "cru",
        "\u039e cru",
        "cru_1",
        "jjjjjjjjjjjjjjjjjjjj"
    ],
    "76561198082380502": [
        "Eddie08",
        "\u039e EDDIE"
    ],
    "76561198082476488": [
        "SBOOO",
        "SBOO",
        "VNGr SBOO",
        "[VNGr] SBOO",
        "[VNGD] SBOO",
        "\u300eV\u300fSBOO",
        "\u300eV\u300fSBOO, the DJ",
        "\u039e SBOOO"
    ],
    "76561198086008280": [
        "Sheller3",
        "\u039e Sheller3",
        "[CAST] Sheller3"
    ],
    "76561198096528814": [
        "Butters",
        "\u039e Butters \u5f61",
        "Butters \u5f61",
        "\u039e Dookie Butter \u5f61",
        "\u039e Mantequilla \u5f61",
        "\u039e Bleach Demon \u5f61",
        "\u039e FlareBitchButters\u5f61",
        "\u039e Butters\u5f61",
        "Butters\u5f61",
        "Mantequillas \u5f61",
        "\u039e UsRanger Acolyte \u5f61",
        "\u039e UsRanger \u5f61"
    ],
    "76561198110273650": [
        "Arcadian",
        "Arcaidan",
        "\u039e Arcaidan"
    ],
    "76561198115926076": [
        "Comrade Grimm",
        "\u039e \u0432\u0438\u0442 | Comrade Grimm"
    ],
    "76561198116869457": [
        "$cripture",
        "\u039e $cripture",
        "\u039e \u0432\u0438\u0442 | $ | \u6210\u90fd",
        "\u039e \u0432\u0438\u0442 | $cripture"
    ],
    "76561198118709046": [
        "Valhalla ",
        "\u039e Valhalla",
        "\u039e Auf Wiedersehen"
    ],
    "76561198118939528": [
        "Hexman",
        "= Hexman"
    ],
    "76561198121072519": [
        "Boomer Sooner",
        "michael152072",
        "= Boomer Sooner",
        "\u039e Boomer Sooner"
    ],
    "76561198122321381": [
        "Relic",
        "\u039e Relic",
        "R\u039elic"
    ],
    "76561198124108211": [
        "LostThatLovingFeeling",
        "\u039e LostThatLovinFeeli",
        "\u039e DickedDownInDallas",
        "Holden_Tudiks",
        "\u039e LostThatLovinFeeling"
    ],
    "76561198125066723": [
        "Kuddles",
        "TheKuddleKing",
        "\u30e1 Kuddles",
        "\u0416\ufe0e | Kuddles"
    ],
    "76561198125692601": [
        "McFudden",
        "\u043d\u0455 | McFudden",
        "-TL- McFudden",
        "\u300bMcFudden",
        "\u0416 | McFudden",
        "\u039e McFudden"
    ],
    "76561198128101122": [
        "Apolo",
        "501st | Apolo",
        "Apolo \u2657",
        "Apolo \u269c",
        "= Apolo",
        "\u039e Apolo",
        "\u1d0eeferpitou",
        "\u1d0eneferpitou",
        "\u1d0en\u039eferpitou",
        "\u1d0enef\u039erpitou",
        "time chamber"
    ],
    "76561198135394723": [
        "FearNaught",
        "\u039e FearNaught",
        "Fearnaught",
        "\u039e Fearnaught"
    ],
    "76561198140054602": [
        "Leeps",
        "Leeps011",
        "[BHB]\u2660Leeps011",
        "[OP/BHB] \u2660 Leeps011",
        "[BHB] Leepapotimis"
    ],
    "76561198141917000": [
        "FreeTheChickens",
        "\u039e FreeTheChickens"
    ],
    "76561198143984857": [
        "Four",
        "=Four",
        "Stoopur",
        "\u039eFour",
        "\u039eSonofSoopurStoopur",
        "I",
        "\u039e R*tf*ck",
        "\u039e \"sUpErTeAm!\"",
        "\u039e I",
        "\u039e Beesecheer",
        "\u039e NomSaiyan",
        "4",
        "Nom...... T1ng",
        "\u039e",
        "< blank >",
        "Rooo Beeeer",
        "[EASY] dAbpbpbps",
        "Rooooo Beer",
        "Hellsgate",
        "Busan"
    ],
    "76561198150864345": [
        "Fignaldo",
        "//Fignaldo",
        "syn | Fignaldo",
        "syn | Fig",
        "\ud800\udc83\ud800\udc83",
        "syn | //Fig",
        "syn | //Fig \u56bc\u69df\u6994",
        "syn | Fig \u56bc\u69df\u6994",
        "syn | BigRigFig",
        "syn | figglesworth",
        "syn | \u56bc\u69df\u6994",
        "\u039e Fignaldo",
        "\u039e Figgy Fugbaldo"
    ],
    "76561198152127858": [
        "Jimbonium",
        "\u2261J\u2261i\u2261M\u2261b\u22610\u2261n\u2261I\u2261u",
        "\u2261 Jimbonium \ud83c\udf4d",
        "FreeThePanther"
    ],
    "76561198154049283": [
        "SongJiang",
        "\u039e songjiang"
    ],
    "76561198157835177": [
        "Three",
        "\u039e Three"
    ],
    "76561198159596884": [
        "Kiwi",
        "\u039e Kiwi"
    ],
    "76561198160089734": [
        "LanQou",
        "\u042fF\u2122 | R. LanQou",
        "\u042fF\u2122 | LanQou",
        "Lan\u00b7Qou",
        "\u039e Lan\u00b7Qou"
    ],
    "76561198160498568": [
        "BrickYak80",
        "\u039e Brick"
    ],
    "76561198162022874": [
        "MrDudeManBagel",
        "Mrdudemanbagel",
        "= Mrdudemanbagel",
        "\u039e Mrdudemanbagel"
    ],
    "76561198165158098": [
        "Turdy Malurdy",
        "[ESPT] Turdy Malurdy",
        "\u039e Turdy Malurdy"
    ],
    "76561198171285683": [
        "Nators",
        "nators",
        "\u039e \u0432\u0438\u0442 | nators"
    ],
    "76561198181514762": [
        "Norosen",
        "[DC] Nosoren",
        "Nosoren",
        "A Horse"
    ],
    "76561198182935191": [
        "Bruv"
    ],
    "76561198190306050": [
        "Kalash",
        "Kalashnikov Hamster",
        "\u039e Kalash"
    ],
    "76561198197169706": [
        "Bonzoo",
        "= Bonzoo",
        "\u039e Bonzoo"
    ],
    "76561198212173485": [
        "Kiralacus",
        "\u039e kiralacus"
    ],
    "76561198243533986": [
        "Excel",
        "\u039e Excel",
        "[COPE] Excel",
        "Not a horse"
    ],
    "76561198257277203": [
        "CstarL7",
        "\u039e CstarL7"
    ],
    "76561198261127488": [
        "GWR14",
        "WestRailwayG"
    ],
    "76561198283748705": [
        "ARES",
        "\u039e ARES",
        "\u039e AR\u039eS"
    ],
    "76561198286348441": [
        "Half Blaked",
        "\u039e Half Blaked"
    ],
    "76561198304795829": [
        "Yuuko (Strik3)",
        "\u039e Str1k3",
        "Str1k3"
    ],
    "76561198311041218": [
        "c9rters",
        "M.Hemulen1985",
        "c9rter"
    ],
    "76561198315721373": [
        "Chokarion",
        "[MS] machinesoldier",
        "Soldier 1",
        "[EXD] The Kid",
        "Chokarion Prime"
    ],
    "76561198321724736": [
        "Koga",
        "\u2661G=N\u2661 Koga",
        "\u039e Koga",
        "\u039e Youtube Koga",
        "\u039e YOUTUBE KOGA"
    ],
    "76561198321748958": [
        "Unknown",
        "\u2020 unknown5463ssj",
        "\u039e unknown",
        "\u039e unknown \u2020",
        "\u039e unknown \u30c4",
        "\u039e UsRanger WAMO GOD",
        "\u039e fuck that shit"
    ],
    "76561198327452831": [
        "CodeaX",
        "= CodeaX",
        "\u039e CodeaX"
    ],
    "76561198336336348": [
        "Epcot_Tiger",
        "\u039e Epcot Tiger"
    ],
    "76561198341346763": [
        "Fligg",
        "\u043d\u0455 | Fligg",
        "-TL- Fligg",
        "GSO.Fligg",
        "Shitter # 1",
        "syn | Fligg",
        "\uff92 Fligg",
        "\u039e Fligg",
        "Fli\u039eger",
        "paracaidista"
    ],
    "76561198347962222": [
        "JimmyVR3",
        "S/Sgt. JimmyVR3 [10t",
        "= JimmyVR3",
        "S/Sgt. Soundpad [10t",
        "Col. JimmyVR3 [10th ",
        "\u039e JimmyVR3"
    ],
    "76561198357050716": [
        "Itsuka Kotori",
        "= Itsuka Kotori",
        "\u039e Itsuka Kotori"
    ],
    "76561198358415267": [
        "Mosemann",
        "\u039e Mosemann"
    ],
    "76561198367166922": [
        "Adam1776",
        "\u039e Adam1776"
    ],
    "76561198375116217": [
        "Simple Jack",
        "average bob",
        "\u039e Simple Jack"
    ],
    "76561198392936070": [
        "Nacho",
        "nacho",
        "= Nacho",
        "\u039e nacho"
    ],
    "76561198397860261": [
        "Clabsos",
        "\u039e  Clabsos"
    ],
    "76561198398886335": [
        "Villain ",
        "Villain",
        "=Villian",
        "\u039e Villian"
    ],
    "76561198411035254": [
        "COBU",
        "\u039e COBU"
    ],
    "76561198420672933": [
        "Seeker",
        "[BHB] Seeker",
        "= Seeker",
        "\u039e Seeker",
        "\u039e S\u039e\u039ek\u039er",
        "\u039e Seek\u039er",
        "Seek\u039er",
        "\u039e Boomah",
        "\u039e Seeker Kills Arty ",
        "\u2661G\u039eN\u2661 Seeker"
    ],
    "76561198427599679": [
        "FreezingTaz",
        "\u039e FreezingTaz",
        "TimeoftheUrukhai",
        "Julius Echter",
        "\u039e VietDong"
    ],
    "76561198451850579": [
        "Kaonashi",
        "CHMA | Kaonashi",
        "Kao",
        "\u039e kaonashi",
        "\u039e kaonashi\u262f",
        "\u039e kaonashi\u262f\u2661\u5b63\u8d5b\u51a0\u519b",
        "\u039e Kaonashi\u262f\u2661"
    ],
    "76561198805528165": [
        "Stevens",
        "stevens"
    ],
    "76561198805946942": [
        "Ban",
        "\u039e Ban"
    ],
    "76561198824499130": [
        "JonaZ",
        "\u039e MG Jesus",
        "\u039e jonaZzzzzzzzzz",
        "\u039e Nakelele",
        "\u039e jonaZzz\u5927\u9b54\u738b"
    ],
    "76561198845441066": [
        "ShakaZulu",
        "\u039e Shaka Zulu"
    ],
    "76561198845630778": [
        "KPM",
        "\u039e KPM"
    ],
    "76561198849191785": [
        "Tiny",
        "TinyPeenGang",
        "=Tiny",
        "= Tiny",
        "\u039e Tiny"
    ],
    "76561198850967906": [
        "KapN",
        "kapN",
        "= KapN",
        "\u039e KapN",
        "G\u039eN KapN"
    ],
    "76561198851432529": [
        "Killa117"
    ],
    "76561198930375179": [
        "RedStorm",
        "\u039e RedStorm"
    ],
    "76561198932735052": [
        "Easton",
        "easton",
        "\u039e Easton"
    ],
    "76561198966307882": [
        "Erich Hartmann",
        "\u039e Erich Hartmann",
        "\u039e Erich\u30c4Hartmann",
        "\u039e Erich\u32e1Hartmann"
    ],
    "76561198967724882": [
        "Mikee",
        "\u300bmikee",
        "mikee",
        "\ub9c8\uc774\ud06c",
        "= mikee",
        "\u039e mikee",
        "eu talent",
        "\u039e mikee_1",
        "[ESPT] mikee",
        "nightmode"
    ],
    "76561198974460192": [
        "WomanRepellent",
        "Woman Repellent",
        "= Woman Repellent",
        "\u039e WomanRepellent",
        "\u039e WomanRepellent_1"
    ],
    "76561198995790506": [
        "Zi",
        "\u039e Zi"
    ],
    "76561199022358124": [
        "Watermelon",
        "\u039e XIAOGONG\u30b7",
        "\u039e WaterMelon\u30b7"
    ],
    "76561199037665430": [
        "Noctis",
        "\u039e noctis",
        "maybenoctis\u1d57\u1d57\u1d5b"
    ],
    "76561199039406030": [
        "VandiXXVI",
        "\u039e Vandi"
    ],
    "76561199045861119": [
        "Makelele",
        "\u039e  Makelele",
        "\u039e Makelele",
        "JaCkz"
    ],
    "76561199067600731": [
        "Mack",
        "\u039e MACK",
        "\u039e Mack"
    ],
    "76561199068120743": [
        "Father Ted",
        "\u039e Fr. Ted"
    ],
    "76561199074177204": [
        "Noles",
        "\u039e Noles"
    ],
    "76561199074729888": [
        "RustyMoose",
        "RustyNutz",
        "Rusty",
        "\u039e Rusty"
    ],
    "76561199094464307": [
        "Rangoo'ster",
        "\u039e \u042fangoo'"
    ],
    "76561199106632515": [
        "Sanzu",
        "[82AD] Sanzu",
        "Sanzu \u30c4",
        "(WTHr) Sanzu \u30c4",
        "\u039e Sanzu \u30c4",
        "UwU E-Girl \u30c4",
        "X\u2661O",
        "\u039e Sanzu"
    ],
    "76561199109900021": [
        "A Mere Cat",
        "Cpt. A Mere Cat",
        "Cpt. \u039b Mere Cat",
        "Cpt. \u039b\u039e Mere Cat",
        "Capt. \u039b\u039e Mere Cat"
    ],
    "76561199139630482": [
        "The Witness",
        "Witness"
    ],
    "76561199162088691": [
        "Hispeedhilly",
        "[ESPT] HiSpeedHilly",
        "\u039e HiSpeedHilly"
    ],
    "76561199165493739": [
        "Megumi Kato",
        "\u039e Megumi Kato"
    ],
    "76561199181811144": [
        "Shadow",
        "\u039e Shadow"
    ],
    "76561199193084753": [
        "Aim",
        "= Albert",
        "= Aim",
        "\u039e FunNyAim",
        "aiM\u039ezzz",
        "\u039e Aimmmzzz",
        "\u039e RadAimz"
    ],
    "76561199251692346": [
        "SeargeantFupa",
        "sergeantfupa",
        "\u039e SergeantFupa",
        "\u039eSergeantfupa",
        "\u039e Sergeantfupa"
    ],
    "76561199381151579": [
        "\ud83c\udd52hanel n\u00b0 303",
        "= \ud83c\udd52hanel n\u00b0 303",
        "\u2661G\u039eN\u2661 \u00ecll n\u00ec\u00f1o",
        "\u00ecll n\u00ec\u00f1o"
    ],
    "76561199382701835": [
        "Blackjak",
        "T/Sgt. Blackjak [10t",
        "=Blackjak",
        "\u039e Blackjak",
        "\u039elackjak",
        "kujo"
    ],
    "76561199518832170": [
        "0.44",
        ".44"
    ],
    "76561199580584956": [
        "Hooded Penny",
        "Hoodedpenny2",
        "\u039e Hoodedpenny"
    ],
    "76561199764854035": [
        "Francis",
        "\u039e Francis\u30c4",
        "(ESPT)Francis\u30c4",
        "\u039e           Francis      \u30c4",
        "Francis .\u039exE \u30c4"
    ]
}